{
	"name": "q1pipeline",
	"properties": {
		"activities": [
			{
				"name": "Copydata From oneserver 2 anothher",
				"type": "ForEach",
				"dependsOn": [],
				"userProperties": [],
				"typeProperties": {
					"items": {
						"value": "@pipeline().parameters.Tablelist",
						"type": "Expression"
					},
					"activities": [
						{
							"name": "Copy data1",
							"type": "Copy",
							"dependsOn": [],
							"policy": {
								"timeout": "7.00:00:00",
								"retry": 0,
								"retryIntervalInSeconds": 30,
								"secureOutput": false,
								"secureInput": false
							},
							"userProperties": [],
							"typeProperties": {
								"source": {
									"type": "SqlServerSource",
									"queryTimeout": "02:00:00",
									"partitionOption": "None"
								},
								"sink": {
									"type": "AzureSqlSink",
									"tableOption": "autoCreate"
								},
								"enableStaging": false,
								"translator": {
									"type": "TabularTranslator",
									"typeConversion": true,
									"typeConversionSettings": {
										"allowDataTruncation": true,
										"treatBooleanAsNumber": false
									}
								}
							},
							"inputs": [
								{
									"referenceName": "AdventureWorkstablesOnpremisesource",
									"type": "DatasetReference",
									"parameters": {
										"TableName": [
											{
												"name": "EmployeeDepartmentHistory"
											}
										]
									}
								}
							],
							"outputs": [
								{
									"referenceName": "AzureSqlTableDestinationq1",
									"type": "DatasetReference"
								}
							]
						}
					]
				}
			}
		],
		"parameters": {
			"Tablelist": {
				"type": "array"
			}
		},
		"annotations": []
	}
}